{
  "contracts": [{"Id":1,"Name":"Yule","Description":"Snooker","ProjectId":1},
{"Id":2,"Name":"Sheridan","Description":"Thermodynamics","ProjectId":1},
{"Id":3,"Name":"Kerry","Description":"HP Servers","ProjectId":1},
{"Id":4,"Name":"Harry","Description":"Contract Negotiation","ProjectId":2},
{"Id":5,"Name":"Clare","Description":"GWAPT","ProjectId":2},
{"Id":6,"Name":"Alyosha","Description":"TPE","ProjectId":2},
{"Id":7,"Name":"Jacenta","Description":"GDI+","ProjectId":3},
{"Id":8,"Name":"Weber","Description":"Light Rail","ProjectId":3},
{"Id":9,"Name":"Rockie","Description":"Sales Management","ProjectId":3},
{"Id":10,"Name":"Rivalee","Description":"Corporate Communications","ProjectId":4},
{"Id":11,"Name":"Norry","Description":"JSF","ProjectId":4},
{"Id":12,"Name":"Alejandra","Description":"Project Implementation","ProjectId":4},
{"Id":13,"Name":"Jerrold","Description":"Access Control","ProjectId":5},
{"Id":14,"Name":"Christa","Description":"RHIT","ProjectId":5},
{"Id":15,"Name":"Dewitt","Description":"Time Series Analysis","ProjectId":5},
{"Id":16,"Name":"Tremaine","Description":"Tissue Culture","ProjectId":6},
{"Id":17,"Name":"Jarib","Description":"Agribusiness","ProjectId":6},
{"Id":18,"Name":"Jackie","Description":"Minority Owned","ProjectId":6},
{"Id":19,"Name":"Randie","Description":"FSP","ProjectId":7},
{"Id":20,"Name":"Debbie","Description":"MBE","ProjectId":7},
{"Id":21,"Name":"Elton","Description":"NNMi","ProjectId":7},
{"Id":22,"Name":"Mahala","Description":"Ships","ProjectId":8},
{"Id":23,"Name":"Jed","Description":"Thermal Oxidation","ProjectId":8},
{"Id":24,"Name":"Nathanael","Description":"Market Knowledge","ProjectId":8},
{"Id":25,"Name":"Adan","Description":"Navy","ProjectId":9},
{"Id":26,"Name":"Fraser","Description":"T-SQL Stored Procedures","ProjectId":9},
{"Id":27,"Name":"Tanny","Description":"Type 2 Diabetes","ProjectId":9},
{"Id":28,"Name":"Kellen","Description":"Eurocodes","ProjectId":10},
{"Id":29,"Name":"Lydie","Description":"MXG","ProjectId":10},
{"Id":30,"Name":"Madel","Description":"Web Analytics","ProjectId":10}]
  ,
  "projects": [{"Id":1,"Name":"Friedrich","Description":"FX Options","PlanId":1},
  {"Id":2,"Name":"Angelina","Description":"MDOP","PlanId":1},
  {"Id":3,"Name":"Mateo","Description":"Make vs Buy","PlanId":1},
  {"Id":4,"Name":"Trumaine","Description":"Hotel Management","PlanId":2},
  {"Id":5,"Name":"Jordana","Description":"Family Law","PlanId":2},
  {"Id":6,"Name":"Eilis","Description":"MVA","PlanId":2},
  {"Id":7,"Name":"Winonah","Description":"Ukulele","PlanId":3},
  {"Id":8,"Name":"Caroljean","Description":"Komodo","PlanId":3},
  {"Id":9,"Name":"Tabbie","Description":"FBD","PlanId":4},
  {"Id":10,"Name":"Aldous","Description":"LC-MS","PlanId":4},
  {"Id":11,"Name":"Penny","Description":"Axles","PlanId":4},
  {"Id":12,"Name":"Mandie","Description":"Agrochemicals","PlanId":4},
  {"Id":13,"Name":"Conni","Description":"RFI","PlanId":5},
  {"Id":14,"Name":"Lenka","Description":"Microsoft Dynamics","PlanId":5},
  {"Id":15,"Name":"Barry","Description":"GNU Radio","PlanId":6},
  {"Id":16,"Name":"Meir","Description":"Overall Wellness","PlanId":6},
  {"Id":17,"Name":"Emmaline","Description":"RV","PlanId":6},
  {"Id":18,"Name":"Vevay","Description":"SNL","PlanId":7},
  {"Id":19,"Name":"Bobbette","Description":"Client Relations","PlanId":7},
  {"Id":20,"Name":"Aeriela","Description":"Hydrology","PlanId":7},
  {"Id":21,"Name":"Ettie","Description":"ISDN","PlanId":8},
  {"Id":22,"Name":"Drucie","Description":"Nikon","PlanId":8},
  {"Id":23,"Name":"Norri","Description":"Lustre","PlanId":8},
  {"Id":24,"Name":"Enid","Description":"Sleep Apnea","PlanId":9},
  {"Id":25,"Name":"Patty","Description":"R&amp;TTE","PlanId":9},
  {"Id":26,"Name":"Blinny","Description":"Personal Injury","PlanId":9},
  {"Id":27,"Name":"Gil","Description":"VLSM","PlanId":10},
  {"Id":28,"Name":"Conn","Description":"Hyperion HFM","PlanId":10},
  {"Id":29,"Name":"Benny","Description":"Publishing","PlanId":10},
  {"Id":30,"Name":"Inga","Description":"DNA electrophoresis","PlanId":10}],
  "plans": [{"Id":1,"Name":"Maison","Description":"GMRA"},
  {"Id":2,"Name":"Reade","Description":"Electrical Controls"},
  {"Id":3,"Name":"Alano","Description":"Oracle Identity Manager"},
  {"Id":4,"Name":"Fidel","Description":"FSP"},
  {"Id":5,"Name":"Nicky","Description":"MP3"},
  {"Id":6,"Name":"Gardiner","Description":"VC#"},
  {"Id":7,"Name":"Dianne","Description":"Sap Fm"},
  {"Id":8,"Name":"Carri","Description":"Thought Leadership"},
  {"Id":9,"Name":"Crissy","Description":"NNMi"},
  {"Id":10,"Name":"Ambrosi","Description":"WordPerfect"},
  {"Id":11,"Name":"Ogden","Description":"Octave"},
  {"Id":12,"Name":"Carolyn","Description":"Jewish Studies"},
  {"Id":13,"Name":"Jenn","Description":"IBC"},
  {"Id":14,"Name":"Claudian","Description":"Clinical Development"},
  {"Id":15,"Name":"Merwin","Description":"FS-CD"},
  {"Id":16,"Name":"Bonnibelle","Description":"Title IV"},
  {"Id":17,"Name":"Ettore","Description":"CCNA"},
  {"Id":18,"Name":"Byrann","Description":"Valves"},
  {"Id":19,"Name":"Skipper","Description":"GWAPT"},
  {"Id":20,"Name":"Hadley","Description":"Cisco MDS SAN switches"},
  {"Id":21,"Name":"Goldina","Description":"Utility Locating"},
  {"Id":22,"Name":"Elfreda","Description":"XLSTAT"},
  {"Id":23,"Name":"Simonette","Description":".htaccess"},
  {"Id":24,"Name":"Eolande","Description":"Ion Exchange"},
  {"Id":25,"Name":"Annadiane","Description":"iReport"},
  {"Id":26,"Name":"Emogene","Description":"Trade Marketing"},
  {"Id":27,"Name":"Lauren","Description":"Ayurveda"},
  {"Id":28,"Name":"Calvin","Description":"Mixed-Signal IC Design"},
  {"Id":29,"Name":"Eada","Description":"WPA"},
  {"Id":30,"Name":"Tomi","Description":"Two-photon Microscopy"}],
  "milestonesStatus":[{"Id":1,"Name":"Nickolas","ActualProgress":1,"Deviation":1,"ScheduleProgress":1},
{"Id":2,"Name":"Leroy","ActualProgress":2,"Deviation":2,"ScheduleProgress":2},
{"Id":3,"Name":"Mervin","ActualProgress":3,"Deviation":3,"ScheduleProgress":3},
{"Id":4,"Name":"Teriann","ActualProgress":4,"Deviation":4,"ScheduleProgress":4},
{"Id":5,"Name":"Isa","ActualProgress":5,"Deviation":5,"ScheduleProgress":5},
{"Id":6,"Name":"Chase","ActualProgress":6,"Deviation":6,"ScheduleProgress":6},
{"Id":7,"Name":"Alair","ActualProgress":7,"Deviation":7,"ScheduleProgress":7},
{"Id":8,"Name":"Trey","ActualProgress":8,"Deviation":8,"ScheduleProgress":8},
{"Id":9,"Name":"Gwynne","ActualProgress":9,"Deviation":9,"ScheduleProgress":9},
{"Id":10,"Name":"Amandy","ActualProgress":10,"Deviation":10,"ScheduleProgress":10},
{"Id":11,"Name":"Pip","ActualProgress":11,"Deviation":11,"ScheduleProgress":11},
{"Id":12,"Name":"Wallis","ActualProgress":12,"Deviation":12,"ScheduleProgress":12},
{"Id":13,"Name":"Amara","ActualProgress":13,"Deviation":13,"ScheduleProgress":13},
{"Id":14,"Name":"Dino","ActualProgress":14,"Deviation":14,"ScheduleProgress":14},
{"Id":15,"Name":"Toma","ActualProgress":15,"Deviation":15,"ScheduleProgress":15},
{"Id":16,"Name":"Orin","ActualProgress":16,"Deviation":16,"ScheduleProgress":16},
{"Id":17,"Name":"Leeann","ActualProgress":17,"Deviation":17,"ScheduleProgress":17},
{"Id":18,"Name":"Ira","ActualProgress":18,"Deviation":18,"ScheduleProgress":18},
{"Id":19,"Name":"Harp","ActualProgress":19,"Deviation":19,"ScheduleProgress":19},
{"Id":20,"Name":"Marie","ActualProgress":20,"Deviation":20,"ScheduleProgress":20},
{"Id":21,"Name":"Ferd","ActualProgress":21,"Deviation":21,"ScheduleProgress":21},
{"Id":22,"Name":"Hazel","ActualProgress":22,"Deviation":22,"ScheduleProgress":22},
{"Id":23,"Name":"Piotr","ActualProgress":23,"Deviation":23,"ScheduleProgress":23},
{"Id":24,"Name":"Baryram","ActualProgress":24,"Deviation":24,"ScheduleProgress":24},
{"Id":25,"Name":"Christy","ActualProgress":25,"Deviation":25,"ScheduleProgress":25},
{"Id":26,"Name":"Brigg","ActualProgress":26,"Deviation":26,"ScheduleProgress":26},
{"Id":27,"Name":"Ted","ActualProgress":27,"Deviation":27,"ScheduleProgress":27},
{"Id":28,"Name":"Wyndham","ActualProgress":28,"Deviation":28,"ScheduleProgress":28},
{"Id":29,"Name":"Eddie","ActualProgress":29,"Deviation":29,"ScheduleProgress":29},
{"Id":30,"Name":"Anne-marie","ActualProgress":30,"Deviation":30,"ScheduleProgress":30}],
  "roles":[{"Id":1,"RoleName":"Attkins","Description":"Del Attkins"},
  {"Id":2,"RoleName":"Basini-Gazzi","Description":"Morley Basini-Gazzi"},
  {"Id":3,"RoleName":"Conkey","Description":"Barny Conkey"},
  {"Id":4,"RoleName":"Dumper","Description":"Virgilio Dumper"},
  {"Id":5,"RoleName":"Rudolf","Description":"Tammy Rudolf"},
  {"Id":6,"RoleName":"Roadnight","Description":"Milo Roadnight"},
  {"Id":7,"RoleName":"Cockney","Description":"Thor Cockney"},
  {"Id":8,"RoleName":"Batho","Description":"Laural Batho"},
  {"Id":9,"RoleName":"Kik","Description":"Tamar Kik"},
  {"Id":10,"RoleName":"MacKessock","Description":"Estrella MacKessock"},
  {"Id":11,"RoleName":"Lancetter","Description":"Obadiah Lancetter"},
  {"Id":12,"RoleName":"Stillman","Description":"Powell Stillman"},
  {"Id":13,"RoleName":"Ulrik","Description":"Wilden Ulrik"},
  {"Id":14,"RoleName":"Helks","Description":"Camella Helks"},
  {"Id":15,"RoleName":"Woodcraft","Description":"Cristabel Woodcraft"},
  {"Id":16,"RoleName":"Augustine","Description":"Glenden Augustine"},
  {"Id":17,"RoleName":"Jaggard","Description":"Bil Jaggard"},
  {"Id":18,"RoleName":"Dewes","Description":"Tobe Dewes"},
  {"Id":19,"RoleName":"Gwillym","Description":"Terrel Gwillym"},
  {"Id":20,"RoleName":"Forton","Description":"Harriet Forton"}],
  "users":[{"Id":1,"FirstName":"Levey","LastName":"Ditchett","IsActive":true,"Email":"lditchett0@army.mil","MustChangePass":false,"Username":"lditchett0","Password":"XzhOdiUtwF","CreateDate":"1/2/2018"},
  {"Id":2,"FirstName":"Stinky","LastName":"Opdenort","IsActive":true,"Email":"sopdenort1@toplist.cz","MustChangePass":false,"Username":"sopdenort1","Password":"QWQCHSJzb","CreateDate":"2/10/2018"},
  {"Id":3,"FirstName":"Ashlan","LastName":"Hardwicke","IsActive":true,"Email":"ahardwicke2@answers.com","MustChangePass":false,"Username":"ahardwicke2","Password":"osucb3","CreateDate":"12/21/2017"},
  {"Id":4,"FirstName":"Dev","LastName":"McKennan","IsActive":false,"Email":"dmckennan3@1und1.de","MustChangePass":true,"Username":"dmckennan3","Password":"L4AUUclz","CreateDate":"3/11/2018"},
  {"Id":5,"FirstName":"Martie","LastName":"Dallyn","IsActive":true,"Email":"mdallyn4@constantcontact.com","MustChangePass":false,"Username":"mdallyn4","Password":"EzZIngb","CreateDate":"9/6/2018"},
  {"Id":6,"FirstName":"Shellysheldon","LastName":"McGarrahan","IsActive":false,"Email":"smcgarrahan5@sohu.com","MustChangePass":false,"Username":"smcgarrahan5","Password":"BXrTI1nyaL","CreateDate":"5/8/2018"},
  {"Id":7,"FirstName":"Tonie","LastName":"Shitliff","IsActive":false,"Email":"tshitliff6@about.com","MustChangePass":true,"Username":"tshitliff6","Password":"lPGqpWFEEWou","CreateDate":"6/21/2018"},
  {"Id":8,"FirstName":"Cathi","LastName":"MacPake","IsActive":false,"Email":"cmacpake7@uol.com.br","MustChangePass":false,"Username":"cmacpake7","Password":"dLSLjQqeTH","CreateDate":"3/22/2018"},
  {"Id":9,"FirstName":"Connie","LastName":"Scarfe","IsActive":true,"Email":"cscarfe8@sfgate.com","MustChangePass":true,"Username":"cscarfe8","Password":"8xmgBu4CQk7","CreateDate":"5/23/2018"},
  {"Id":10,"FirstName":"Alexandros","LastName":"Tummond","IsActive":true,"Email":"atummond9@pinterest.com","MustChangePass":true,"Username":"atummond9","Password":"9LljM9bwu06y","CreateDate":"10/6/2018"},
  {"Id":11,"FirstName":"Tirrell","LastName":"Hatrey","IsActive":true,"Email":"thatreya@tinyurl.com","MustChangePass":false,"Username":"thatreya","Password":"HFsgeOdSpJF5","CreateDate":"1/16/2018"},
  {"Id":12,"FirstName":"Godiva","LastName":"Seeking","IsActive":true,"Email":"gseekingb@bloglines.com","MustChangePass":false,"Username":"gseekingb","Password":"036F1O","CreateDate":"6/2/2018"},
  {"Id":13,"FirstName":"Phylis","LastName":"Champneys","IsActive":false,"Email":"pchampneysc@naver.com","MustChangePass":false,"Username":"pchampneysc","Password":"c40mU2","CreateDate":"6/16/2018"},
  {"Id":14,"FirstName":"Meredithe","LastName":"Weed","IsActive":true,"Email":"mweedd@feedburner.com","MustChangePass":false,"Username":"mweedd","Password":"SNkMxQipkqU","CreateDate":"4/7/2018"},
  {"Id":15,"FirstName":"Connie","LastName":"Lowres","IsActive":true,"Email":"clowrese@lycos.com","MustChangePass":false,"Username":"clowrese","Password":"fMUKRzhXIjAT","CreateDate":"8/8/2018"},
  {"Id":16,"FirstName":"Arly","LastName":"Wortman","IsActive":false,"Email":"awortmanf@wikia.com","MustChangePass":true,"Username":"awortmanf","Password":"yc71s9BT4","CreateDate":"12/6/2018"},
  {"Id":17,"FirstName":"Dev","LastName":"Haibel","IsActive":true,"Email":"dhaibelg@example.com","MustChangePass":false,"Username":"dhaibelg","Password":"hyXwI3K","CreateDate":"7/23/2018"},
  {"Id":18,"FirstName":"Florri","LastName":"Royl","IsActive":false,"Email":"froylh@woothemes.com","MustChangePass":false,"Username":"froylh","Password":"0rH2MvnHG0","CreateDate":"8/19/2018"},
  {"Id":19,"FirstName":"Coralie","LastName":"Gasker","IsActive":false,"Email":"cgaskeri@google.com.au","MustChangePass":false,"Username":"cgaskeri","Password":"FbU6MjTE","CreateDate":"1/9/2018"},
  {"Id":20,"FirstName":"Padraic","LastName":"Dent","IsActive":false,"Email":"pdentj@arstechnica.com","MustChangePass":false,"Username":"pdentj","Password":"iQ6IE5WJw","CreateDate":"4/6/2018"},
  {"Id":21,"FirstName":"Travis","LastName":"Burden","IsActive":false,"Email":"tburdenk@cnet.com","MustChangePass":false,"Username":"tburdenk","Password":"dl7okhHLwIL","CreateDate":"8/6/2018"},
  {"Id":22,"FirstName":"Ferne","LastName":"Yousef","IsActive":true,"Email":"fyousefl@i2i.jp","MustChangePass":false,"Username":"fyousefl","Password":"p26ECENcnwN","CreateDate":"3/28/2018"},
  {"Id":23,"FirstName":"Paten","LastName":"Cotmore","IsActive":true,"Email":"pcotmorem@tinypic.com","MustChangePass":true,"Username":"pcotmorem","Password":"437GsJHAHw","CreateDate":"8/14/2018"},
  {"Id":24,"FirstName":"Stacia","LastName":"Meert","IsActive":false,"Email":"smeertn@t-online.de","MustChangePass":false,"Username":"smeertn","Password":"I6D1xS","CreateDate":"3/6/2018"},
  {"Id":25,"FirstName":"Vannie","LastName":"Claxson","IsActive":false,"Email":"vclaxsono@businesswire.com","MustChangePass":true,"Username":"vclaxsono","Password":"oUihThZih","CreateDate":"5/18/2018"},
  {"Id":26,"FirstName":"Wenona","LastName":"Choke","IsActive":true,"Email":"wchokep@mozilla.org","MustChangePass":false,"Username":"wchokep","Password":"UmBlqp","CreateDate":"3/17/2018"},
  {"Id":27,"FirstName":"Grant","LastName":"Maylour","IsActive":true,"Email":"gmaylourq@is.gd","MustChangePass":true,"Username":"gmaylourq","Password":"6PpG4tokwyp","CreateDate":"1/27/2018"},
  {"Id":28,"FirstName":"Judith","LastName":"Thunderman","IsActive":true,"Email":"jthundermanr@upenn.edu","MustChangePass":true,"Username":"jthundermanr","Password":"ZLERuGG55fD","CreateDate":"4/24/2018"},
  {"Id":29,"FirstName":"Jenda","LastName":"MacEllen","IsActive":true,"Email":"jmacellens@rediff.com","MustChangePass":false,"Username":"jmacellens","Password":"FDCChHAlVP","CreateDate":"10/20/2018"},
  {"Id":30,"FirstName":"Mab","LastName":"Iddens","IsActive":true,"Email":"middenst@google.ca","MustChangePass":false,"Username":"middenst","Password":"rScOsB","CreateDate":"10/26/2018"},
  {"Id":31,"FirstName":"Cheslie","LastName":"Hamstead","IsActive":false,"Email":"chamsteadu@joomla.org","MustChangePass":false,"Username":"chamsteadu","Password":"U3mVN5l","CreateDate":"5/30/2018"},
  {"Id":32,"FirstName":"Arty","LastName":"Mallabund","IsActive":true,"Email":"amallabundv@noaa.gov","MustChangePass":false,"Username":"amallabundv","Password":"Nw2VDXZmpy9V","CreateDate":"3/3/2018"},
  {"Id":33,"FirstName":"Luca","LastName":"Kendred","IsActive":false,"Email":"lkendredw@telegraph.co.uk","MustChangePass":true,"Username":"lkendredw","Password":"6lnJNybE","CreateDate":"11/15/2018"},
  {"Id":34,"FirstName":"Golda","LastName":"Richford","IsActive":false,"Email":"grichfordx@dropbox.com","MustChangePass":false,"Username":"grichfordx","Password":"xV4KjqNtq0u","CreateDate":"10/12/2018"},
  {"Id":35,"FirstName":"Faye","LastName":"McGaughie","IsActive":false,"Email":"fmcgaughiey@tmall.com","MustChangePass":false,"Username":"fmcgaughiey","Password":"om9EogIFI","CreateDate":"7/28/2018"},
  {"Id":36,"FirstName":"Alanson","LastName":"Allenson","IsActive":false,"Email":"aallensonz@booking.com","MustChangePass":false,"Username":"aallensonz","Password":"e7Z8VXfd7REM","CreateDate":"7/16/2018"},
  {"Id":37,"FirstName":"Camey","LastName":"Petel","IsActive":true,"Email":"cpetel10@usnews.com","MustChangePass":true,"Username":"cpetel10","Password":"p3rRTef0dEm","CreateDate":"2/12/2018"},
  {"Id":38,"FirstName":"Victor","LastName":"Henderson","IsActive":true,"Email":"vhenderson11@hubpages.com","MustChangePass":true,"Username":"vhenderson11","Password":"pkA0QAwe85U","CreateDate":"8/5/2018"},
  {"Id":39,"FirstName":"Edlin","LastName":"Clemoes","IsActive":false,"Email":"eclemoes12@t-online.de","MustChangePass":true,"Username":"eclemoes12","Password":"9IqaCnjS","CreateDate":"7/29/2018"},
  {"Id":40,"FirstName":"Geno","LastName":"Binks","IsActive":false,"Email":"gbinks13@engadget.com","MustChangePass":true,"Username":"gbinks13","Password":"w1FR5Yknsvfm","CreateDate":"7/7/2018"},
  {"Id":41,"FirstName":"Mikaela","LastName":"Gepp","IsActive":true,"Email":"mgepp14@fastcompany.com","MustChangePass":false,"Username":"mgepp14","Password":"odwKXH01C","CreateDate":"12/2/2018"},
  {"Id":42,"FirstName":"Jedediah","LastName":"Ritzman","IsActive":false,"Email":"jritzman15@weebly.com","MustChangePass":false,"Username":"jritzman15","Password":"abAFTwn","CreateDate":"9/22/2018"},
  {"Id":43,"FirstName":"Rachelle","LastName":"Oseland","IsActive":false,"Email":"roseland16@tripadvisor.com","MustChangePass":false,"Username":"roseland16","Password":"ThkVVA1","CreateDate":"1/18/2018"},
  {"Id":44,"FirstName":"Olimpia","LastName":"Vinsen","IsActive":true,"Email":"ovinsen17@tamu.edu","MustChangePass":true,"Username":"ovinsen17","Password":"hCeyZPy","CreateDate":"4/2/2018"},
  {"Id":45,"FirstName":"Arley","LastName":"Jakeway","IsActive":false,"Email":"ajakeway18@prlog.org","MustChangePass":false,"Username":"ajakeway18","Password":"x31Yma","CreateDate":"12/12/2018"},
  {"Id":46,"FirstName":"Shanta","LastName":"Paur","IsActive":true,"Email":"spaur19@nydailynews.com","MustChangePass":false,"Username":"spaur19","Password":"tKlhVDSK","CreateDate":"3/3/2018"},
  {"Id":47,"FirstName":"Milicent","LastName":"Vela","IsActive":false,"Email":"mvela1a@phpbb.com","MustChangePass":true,"Username":"mvela1a","Password":"9srRt0aL","CreateDate":"12/10/2018"},
  {"Id":48,"FirstName":"Noelle","LastName":"Yarnell","IsActive":false,"Email":"nyarnell1b@infoseek.co.jp","MustChangePass":false,"Username":"nyarnell1b","Password":"hQe2Lqi1","CreateDate":"7/22/2018"},
  {"Id":49,"FirstName":"Aloise","LastName":"Kilgrew","IsActive":false,"Email":"akilgrew1c@reddit.com","MustChangePass":true,"Username":"akilgrew1c","Password":"QjEHdBRQ","CreateDate":"12/19/2017"},
  {"Id":50,"FirstName":"Lorie","LastName":"Castelletti","IsActive":false,"Email":"lcastelletti1d@yelp.com","MustChangePass":true,"Username":"lcastelletti1d","Password":"2zCajo","CreateDate":"3/20/2018"}],
  "companies":[{"Id":1,"Name":"Florry"},
{"Id":2,"Name":"Milicent"},
{"Id":3,"Name":"Ripley"},
{"Id":4,"Name":"Forest"},
{"Id":5,"Name":"Natka"},
{"Id":6,"Name":"Sharai"},
{"Id":7,"Name":"Debee"},
{"Id":8,"Name":"Tedda"},
{"Id":9,"Name":"Christine"},
{"Id":10,"Name":"Lyndell"},
{"Id":11,"Name":"Halley"},
{"Id":12,"Name":"Fawne"},
{"Id":13,"Name":"Leela"},
{"Id":14,"Name":"Lauryn"},
{"Id":15,"Name":"Andrew"},
{"Id":16,"Name":"Garnette"},
{"Id":17,"Name":"Agneta"},
{"Id":18,"Name":"Hyatt"},
{"Id":19,"Name":"Angy"},
{"Id":20,"Name":"Imojean"},
{"Id":21,"Name":"Torey"},
{"Id":22,"Name":"Urbain"},
{"Id":23,"Name":"Jarrod"},
{"Id":24,"Name":"Hy"},
{"Id":25,"Name":"Flss"},
{"Id":26,"Name":"Inessa"},
{"Id":27,"Name":"Armstrong"},
{"Id":28,"Name":"Gannie"},
{"Id":29,"Name":"Konrad"},
{"Id":30,"Name":"Alex"}],
  "schedule":[{"Id":1,"ActivitiesId":1,"SatartDate":"2/28/2018","FinishDate":"1/2/2018"},
{"Id":2,"ActivitiesId":2,"SatartDate":"5/13/2018","FinishDate":"1/5/2018"},
{"Id":3,"ActivitiesId":3,"SatartDate":"8/31/2018","FinishDate":"8/31/2018"},
{"Id":4,"ActivitiesId":4,"SatartDate":"3/20/2018","FinishDate":"1/12/2018"},
{"Id":5,"ActivitiesId":5,"SatartDate":"2/21/2018","FinishDate":"7/18/2018"},
{"Id":6,"ActivitiesId":6,"SatartDate":"3/18/2018","FinishDate":"8/10/2018"},
{"Id":7,"ActivitiesId":7,"SatartDate":"12/16/2017","FinishDate":"5/5/2018"},
{"Id":8,"ActivitiesId":8,"SatartDate":"3/7/2018","FinishDate":"11/2/2018"},
{"Id":9,"ActivitiesId":9,"SatartDate":"5/22/2018","FinishDate":"5/14/2018"},
{"Id":10,"ActivitiesId":10,"SatartDate":"5/28/2018","FinishDate":"8/14/2018"},
{"Id":11,"ActivitiesId":11,"SatartDate":"8/13/2018","FinishDate":"9/16/2018"},
{"Id":12,"ActivitiesId":12,"SatartDate":"1/17/2018","FinishDate":"11/12/2018"},
{"Id":13,"ActivitiesId":13,"SatartDate":"4/3/2018","FinishDate":"8/24/2018"},
{"Id":14,"ActivitiesId":14,"SatartDate":"5/21/2018","FinishDate":"1/25/2018"},
{"Id":15,"ActivitiesId":15,"SatartDate":"8/6/2018","FinishDate":"7/26/2018"},
{"Id":16,"ActivitiesId":16,"SatartDate":"10/16/2018","FinishDate":"5/21/2018"},
{"Id":17,"ActivitiesId":17,"SatartDate":"4/2/2018","FinishDate":"8/25/2018"},
{"Id":18,"ActivitiesId":18,"SatartDate":"8/18/2018","FinishDate":"6/9/2018"},
{"Id":19,"ActivitiesId":19,"SatartDate":"7/22/2018","FinishDate":"2/24/2018"},
{"Id":20,"ActivitiesId":20,"SatartDate":"12/16/2017","FinishDate":"10/8/2018"},
{"Id":21,"ActivitiesId":21,"SatartDate":"4/14/2018","FinishDate":"12/16/2017"},
{"Id":22,"ActivitiesId":22,"SatartDate":"10/22/2018","FinishDate":"1/13/2018"},
{"Id":23,"ActivitiesId":23,"SatartDate":"12/26/2017","FinishDate":"3/27/2018"},
{"Id":24,"ActivitiesId":24,"SatartDate":"1/28/2018","FinishDate":"1/17/2018"},
{"Id":25,"ActivitiesId":25,"SatartDate":"3/26/2018","FinishDate":"5/7/2018"},
{"Id":26,"ActivitiesId":26,"SatartDate":"7/15/2018","FinishDate":"1/12/2018"},
{"Id":27,"ActivitiesId":27,"SatartDate":"5/18/2018","FinishDate":"6/9/2018"},
{"Id":28,"ActivitiesId":28,"SatartDate":"5/22/2018","FinishDate":"7/26/2018"},
{"Id":29,"ActivitiesId":29,"SatartDate":"2/21/2018","FinishDate":"9/26/2018"},
{"Id":30,"ActivitiesId":30,"SatartDate":"4/5/2018","FinishDate":"12/20/2017"}],
  "progresses":[{"Id":1,"ActivitiesId":1,"Day":"6/15/2018","IsDone":true,"PersonInChargeId":1},
  {"Id":2,"ActivitiesId":2,"Day":"8/17/2018","IsDone":false,"PersonInChargeId":2},
  {"Id":3,"ActivitiesId":3,"Day":"12/16/2017","IsDone":false,"PersonInChargeId":3},
  {"Id":4,"ActivitiesId":4,"Day":"2/7/2018","IsDone":false,"PersonInChargeId":4},
  {"Id":5,"ActivitiesId":5,"Day":"1/29/2018","IsDone":false,"PersonInChargeId":5},
  {"Id":6,"ActivitiesId":6,"Day":"1/26/2018","IsDone":false,"PersonInChargeId":6},
  {"Id":7,"ActivitiesId":7,"Day":"3/13/2018","IsDone":true,"PersonInChargeId":7},
  {"Id":8,"ActivitiesId":8,"Day":"11/9/2018","IsDone":true,"PersonInChargeId":8},
  {"Id":9,"ActivitiesId":9,"Day":"2/26/2018","IsDone":false,"PersonInChargeId":9},
  {"Id":10,"ActivitiesId":10,"Day":"6/27/2018","IsDone":false,"PersonInChargeId":10},
  {"Id":11,"ActivitiesId":11,"Day":"10/14/2018","IsDone":false,"PersonInChargeId":11},
  {"Id":12,"ActivitiesId":12,"Day":"3/27/2018","IsDone":false,"PersonInChargeId":12},
  {"Id":13,"ActivitiesId":13,"Day":"9/14/2018","IsDone":false,"PersonInChargeId":13},
  {"Id":14,"ActivitiesId":14,"Day":"6/22/2018","IsDone":true,"PersonInChargeId":14},
  {"Id":15,"ActivitiesId":15,"Day":"3/24/2018","IsDone":true,"PersonInChargeId":15},
  {"Id":16,"ActivitiesId":16,"Day":"4/9/2018","IsDone":true,"PersonInChargeId":16},
  {"Id":17,"ActivitiesId":17,"Day":"6/16/2018","IsDone":true,"PersonInChargeId":17},
  {"Id":18,"ActivitiesId":18,"Day":"4/27/2018","IsDone":false,"PersonInChargeId":18},
  {"Id":19,"ActivitiesId":19,"Day":"4/11/2018","IsDone":true,"PersonInChargeId":19},
  {"Id":20,"ActivitiesId":20,"Day":"3/8/2018","IsDone":false,"PersonInChargeId":20},
  {"Id":21,"ActivitiesId":21,"Day":"1/21/2018","IsDone":true,"PersonInChargeId":21},
  {"Id":22,"ActivitiesId":22,"Day":"5/5/2018","IsDone":false,"PersonInChargeId":22},
  {"Id":23,"ActivitiesId":23,"Day":"4/11/2018","IsDone":false,"PersonInChargeId":23},
  {"Id":24,"ActivitiesId":24,"Day":"7/18/2018","IsDone":true,"PersonInChargeId":24},
  {"Id":25,"ActivitiesId":25,"Day":"11/22/2018","IsDone":true,"PersonInChargeId":25},
  {"Id":26,"ActivitiesId":26,"Day":"12/20/2017","IsDone":false,"PersonInChargeId":26},
  {"Id":27,"ActivitiesId":27,"Day":"8/4/2018","IsDone":true,"PersonInChargeId":27},
  {"Id":28,"ActivitiesId":28,"Day":"3/21/2018","IsDone":false,"PersonInChargeId":28},
  {"Id":29,"ActivitiesId":29,"Day":"12/19/2017","IsDone":false,"PersonInChargeId":29},
  {"Id":30,"ActivitiesId":30,"Day":"11/1/2018","IsDone":false,"PersonInChargeId":30}],
  "milestones":[{"Id":1,"Code":"CNY","Name":"Jacquetta","MeetDate":"10/22/2018","Description":"Re-engineered attitude-oriented standardization","DisciplineId":1,"ContractId":1},
{"Id":2,"Code":"RUB","Name":"Torrin","MeetDate":"7/1/2018","Description":"Synergized 3rd generation internet solution","DisciplineId":2,"ContractId":2},
{"Id":3,"Code":"IdR","Name":"Jose","MeetDate":"10/7/2018","Description":"Synergistic secondary mIddleware","DisciplineId":3,"ContractId":3},
{"Id":4,"Code":"CNY","Name":"Selma","MeetDate":"10/23/2018","Description":"Re-engineered holistic superstructure","DisciplineId":4,"ContractId":4},
{"Id":5,"Code":"USD","Name":"Sibella","MeetDate":"12/4/2018","Description":"Multi-layered foreground analyzer","DisciplineId":5,"ContractId":5},
{"Id":6,"Code":"CNY","Name":"Margette","MeetDate":"12/21/2017","Description":"Front-line eco-centric hub","DisciplineId":6,"ContractId":6},
{"Id":7,"Code":"KRW","Name":"Inessa","MeetDate":"6/26/2018","Description":"Compatible responsive mIddleware","DisciplineId":7,"ContractId":7},
{"Id":8,"Code":"RUB","Name":"Donica","MeetDate":"5/13/2018","Description":"Re-contextualized client-server approach","DisciplineId":8,"ContractId":8},
{"Id":9,"Code":"SEK","Name":"Henriette","MeetDate":"2/14/2018","Description":"Re-engineered 3rd generation encoding","DisciplineId":9,"ContractId":9},
{"Id":10,"Code":"DOP","Name":"Erika","MeetDate":"4/12/2018","Description":"Organized national moratorium","DisciplineId":10,"ContractId":10},
{"Id":11,"Code":"SEK","Name":"Erroll","MeetDate":"5/18/2018","Description":"Upgradable responsive model","DisciplineId":11,"ContractId":11},
{"Id":12,"Code":"EUR","Name":"Biron","MeetDate":"1/25/2018","Description":"User-centric systematic open system","DisciplineId":12,"ContractId":12},
{"Id":13,"Code":"MKD","Name":"Philomena","MeetDate":"1/30/2018","Description":"Quality-focused intangible orchestration","DisciplineId":13,"ContractId":13},
{"Id":14,"Code":"THB","Name":"Dorisa","MeetDate":"7/10/2018","Description":"Total zero defect knowledge user","DisciplineId":14,"ContractId":14},
{"Id":15,"Code":"PEN","Name":"Jeromy","MeetDate":"6/27/2018","Description":"Robust 24 hour strategy","DisciplineId":15,"ContractId":15},
{"Id":16,"Code":"EUR","Name":"Maynord","MeetDate":"1/14/2018","Description":"Synergized solution-oriented framework","DisciplineId":16,"ContractId":16},
{"Id":17,"Code":"AUD","Name":"Royce","MeetDate":"8/31/2018","Description":"Visionary reciprocal extranet","DisciplineId":17,"ContractId":17},
{"Id":18,"Code":"CNY","Name":"Teresita","MeetDate":"3/14/2018","Description":"Persevering maximized definition","DisciplineId":18,"ContractId":18},
{"Id":19,"Code":"PLN","Name":"Ida","MeetDate":"9/25/2018","Description":"Synchronised high-level product","DisciplineId":19,"ContractId":19},
{"Id":20,"Code":"CNY","Name":"Denis","MeetDate":"3/13/2018","Description":"Right-sized interactive capability","DisciplineId":20,"ContractId":20},
{"Id":21,"Code":"MVR","Name":"Douglass","MeetDate":"3/20/2018","Description":"Enhanced national alliance","DisciplineId":21,"ContractId":21},
{"Id":22,"Code":"BRL","Name":"Araldo","MeetDate":"3/3/2018","Description":"Ameliorated disintermediate flexibility","DisciplineId":22,"ContractId":22},
{"Id":23,"Code":"HRK","Name":"Dana","MeetDate":"6/10/2018","Description":"Fully-configurable zero tolerance info-mediaries","DisciplineId":23,"ContractId":23},
{"Id":24,"Code":"BRL","Name":"Kingston","MeetDate":"6/1/2018","Description":"Networked 6th generation mIddleware","DisciplineId":24,"ContractId":24},
{"Id":25,"Code":"IdR","Name":"Domeniga","MeetDate":"3/15/2018","Description":"Visionary mobile process improvement","DisciplineId":25,"ContractId":25},
{"Id":26,"Code":"ALL","Name":"Kippie","MeetDate":"2/17/2018","Description":"Open-architected full-range policy","DisciplineId":26,"ContractId":26},
{"Id":27,"Code":"EUR","Name":"Elisabet","MeetDate":"8/8/2018","Description":"User-friendly user-facing secured line","DisciplineId":27,"ContractId":27},
{"Id":28,"Code":"SEK","Name":"Paxton","MeetDate":"3/13/2018","Description":"Proactive 6th generation initiative","DisciplineId":28,"ContractId":28},
{"Id":29,"Code":"CNY","Name":"Kathy","MeetDate":"11/7/2018","Description":"Stand-alone 24/7 contingency","DisciplineId":29,"ContractId":29},
{"Id":30,"Code":"VND","Name":"Kyla","MeetDate":"6/25/2018","Description":"Multi-lateral interactive hub","DisciplineId":30,"ContractId":30}],
  "diciplines":[{"Id":1,"Name":"Fenelia","Abbreviation":"KS","CompanyName":"Yadel","CompanyId":1},
{"Id":2,"Name":"Killian","Abbreviation":"TX","CompanyName":"Zooxo","CompanyId":2},
{"Id":3,"Name":"Bucky","Abbreviation":"AR","CompanyName":"Photobug","CompanyId":3},
{"Id":4,"Name":"Kristos","Abbreviation":"FL","CompanyName":"CentIdel","CompanyId":4},
{"Id":5,"Name":"Wye","Abbreviation":"PA","CompanyName":"Babbleset","CompanyId":5},
{"Id":6,"Name":"Domenico","Abbreviation":"FL","CompanyName":"CogIdoo","CompanyId":6},
{"Id":7,"Name":"Morrie","Abbreviation":"DC","CompanyName":"Flashset","CompanyId":7},
{"Id":8,"Name":"Kim","Abbreviation":"VA","CompanyName":"Mydeo","CompanyId":8},
{"Id":9,"Name":"Euell","Abbreviation":"TX","CompanyName":"VIdoo","CompanyId":9},
{"Id":10,"Name":"Rosetta","Abbreviation":"VA","CompanyName":"Plambee","CompanyId":10},
{"Id":11,"Name":"Shannon","Abbreviation":"CO","CompanyName":"Jazzy","CompanyId":11},
{"Id":12,"Name":"Raul","Abbreviation":"DE","CompanyName":"Blogpad","CompanyId":12},
{"Id":13,"Name":"Dieter","Abbreviation":"CA","CompanyName":"Kimia","CompanyId":13},
{"Id":14,"Name":"Jana","Abbreviation":"FL","CompanyName":"Blogpad","CompanyId":14},
{"Id":15,"Name":"Gusty","Abbreviation":"AR","CompanyName":"Oba","CompanyId":15},
{"Id":16,"Name":"Kathryn","Abbreviation":"TX","CompanyName":"Jaxworks","CompanyId":16},
{"Id":17,"Name":"Michal","Abbreviation":"OH","CompanyName":"Lazz","CompanyId":17},
{"Id":18,"Name":"Trescha","Abbreviation":"AL","CompanyName":"Browseblab","CompanyId":18},
{"Id":19,"Name":"Jorrie","Abbreviation":"NY","CompanyName":"Yadel","CompanyId":19},
{"Id":20,"Name":"Karyl","Abbreviation":"GA","CompanyName":"FivebrIdge","CompanyId":20},
{"Id":21,"Name":"Tommy","Abbreviation":"KY","CompanyName":"Avaveo","CompanyId":21},
{"Id":22,"Name":"Christye","Abbreviation":"CA","CompanyName":"Skyvu","CompanyId":22},
{"Id":23,"Name":"Raye","Abbreviation":"TX","CompanyName":"Plajo","CompanyId":23},
{"Id":24,"Name":"Hakim","Abbreviation":"AL","CompanyName":"Jetpulse","CompanyId":24},
{"Id":25,"Name":"Malia","Abbreviation":"TX","CompanyName":"Meeveo","CompanyId":25},
{"Id":26,"Name":"Joyan","Abbreviation":"NY","CompanyName":"Zava","CompanyId":26},
{"Id":27,"Name":"Hobard","Abbreviation":"WV","CompanyName":"Latz","CompanyId":27},
{"Id":28,"Name":"Ophelie","Abbreviation":"TX","CompanyName":"Quimba","CompanyId":28},
{"Id":29,"Name":"Jacinthe","Abbreviation":"KY","CompanyName":"Skyndu","CompanyId":29},
{"Id":30,"Name":"Merilyn","Abbreviation":"IA","CompanyName":"InnoZ","CompanyId":30}],
  "staffs":[{"Id":1,"Name":"Gael","Family":"Issard","Email":"gissard0@redcross.org","CompanyId":1},
  {"Id":2,"Name":"Florentia","Family":"Asel","Email":"fasel1@ox.ac.uk","CompanyId":2},
  {"Id":3,"Name":"Raleigh","Family":"Arlow","Email":"rarlow2@npr.org","CompanyId":3},
  {"Id":4,"Name":"Jordan","Family":"Courcey","Email":"jcourcey3@360.cn","CompanyId":4},
  {"Id":5,"Name":"Tim","Family":"Raw","Email":"traw4@reddit.com","CompanyId":5},
  {"Id":6,"Name":"Letisha","Family":"Diaper","Email":"ldiaper5@vk.com","CompanyId":6},
  {"Id":7,"Name":"Molly","Family":"felip","Email":"mfelip6@nhs.uk","CompanyId":7},
  {"Id":8,"Name":"Tommy","Family":"End","Email":"tend7@npr.org","CompanyId":8},
  {"Id":9,"Name":"Gene","Family":"Thripp","Email":"gthripp8@posterous.com","CompanyId":9},
  {"Id":10,"Name":"Darin","Family":"Purchase","Email":"dpurchase9@princeton.edu","CompanyId":10},
  {"Id":11,"Name":"Viola","Family":"Cremer","Email":"vcremera@surveymonkey.com","CompanyId":11},
  {"Id":12,"Name":"Daffie","Family":"Krikorian","Email":"dkrikorianb@vk.com","CompanyId":12},
  {"Id":13,"Name":"Angel","Family":"Iwanczyk","Email":"aiwanczykc@tmall.com","CompanyId":13},
  {"Id":14,"Name":"Mimi","Family":"Tale","Email":"mtaled@yahoo.co.jp","CompanyId":14},
  {"Id":15,"Name":"Sisely","Family":"Tyers","Email":"styerse@ycombinator.com","CompanyId":15},
  {"Id":16,"Name":"Fifi","Family":"Mityukov","Email":"fmityukovf@shutterfly.com","CompanyId":16},
  {"Id":17,"Name":"Rebecca","Family":"Prover","Email":"rproverg@hatena.ne.jp","CompanyId":17},
  {"Id":18,"Name":"Leslie","Family":"Ilieve","Email":"lilieveh@reference.com","CompanyId":18},
  {"Id":19,"Name":"Marietta","Family":"Soper","Email":"msoperi@rambler.ru","CompanyId":19},
  {"Id":20,"Name":"Rivkah","Family":"Vaillant","Email":"rvaillantj@instagram.com","CompanyId":20},
  {"Id":21,"Name":"Yard","Family":"Geffe","Email":"ygeffek@blog.com","CompanyId":21},
  {"Id":22,"Name":"Carine","Family":"Birdsall","Email":"cbirdsalll@ehow.com","CompanyId":22},
  {"Id":23,"Name":"Rancell","Family":"Hambers","Email":"rhambersm@so-net.ne.jp","CompanyId":23},
  {"Id":24,"Name":"Helaine","Family":"Dorman","Email":"hdormann@theguardian.com","CompanyId":24},
  {"Id":25,"Name":"Hussein","Family":"Cordero","Email":"hcorderoo@usatoday.com","CompanyId":25},
  {"Id":26,"Name":"Mirabel","Family":"Lafond","Email":"mlafondp@aol.com","CompanyId":26},
  {"Id":27,"Name":"Caria","Family":"Sealeaf","Email":"csealeafq@hud.gov","CompanyId":27},
  {"Id":28,"Name":"Leanora","Family":"Rosewall","Email":"lrosewallr@reference.com","CompanyId":28},
  {"Id":29,"Name":"Stacee","Family":"Lindsley","Email":"slindsleys@1688.com","CompanyId":29},
  {"Id":30,"Name":"Joice","Family":"Duffield","Email":"jduffieldt@unicef.org","CompanyId":30}],
  "personincharges":[{"Id":1,"Title":"From Here to Eternity","StaffId":1,"ContarctId":1,"DisciplineId":66},
  {"Id":2,"Title":"Northerners, The (De noorderlingen)","StaffId":2,"ContarctId":2,"DisciplineId":48},
  {"Id":3,"Title":"Land of Milk and Honey (Pays de cocagne)","StaffId":3,"ContarctId":3,"DisciplineId":21},
  {"Id":4,"Title":"Faat Kiné","StaffId":4,"ContarctId":4,"DisciplineId":87},
  {"Id":5,"Title":"The Day I Saw Your Heart","StaffId":5,"ContarctId":5,"DisciplineId":21},
  {"Id":6,"Title":"Pillars of the Earth, The","StaffId":6,"ContarctId":6,"DisciplineId":37},
  {"Id":7,"Title":"Grave Decisions (Wer früher stirbt, ist länger tot)","StaffId":7,"ContarctId":7,"DisciplineId":78},
  {"Id":8,"Title":"Omen, The","StaffId":8,"ContarctId":8,"DisciplineId":76},
  {"Id":9,"Title":"Man Behind the Gun, The","StaffId":9,"ContarctId":9,"DisciplineId":53},
  {"Id":10,"Title":"Equalizer, The","StaffId":10,"ContarctId":10,"DisciplineId":83},
  {"Id":11,"Title":"Funhouse, The","StaffId":11,"ContarctId":11,"DisciplineId":50},
  {"Id":12,"Title":"Tür, Die (Door, The)","StaffId":12,"ContarctId":12,"DisciplineId":92},
  {"Id":13,"Title":"Lady Vanishes, The","StaffId":13,"ContarctId":13,"DisciplineId":39},
  {"Id":14,"Title":"Good Thief, The","StaffId":14,"ContarctId":14,"DisciplineId":74},
  {"Id":15,"Title":"Black Widow","StaffId":15,"ContarctId":15,"DisciplineId":37},
  {"Id":16,"Title":"How Hitler Lost the War","StaffId":16,"ContarctId":16,"DisciplineId":84},
  {"Id":17,"Title":"Zombeavers","StaffId":17,"ContarctId":17,"DisciplineId":78},
  {"Id":18,"Title":"Birdsong (Cant dels ocells, El)","StaffId":18,"ContarctId":18,"DisciplineId":26},
  {"Id":19,"Title":"Adonis Factor, The","StaffId":19,"ContarctId":19,"DisciplineId":68},
  {"Id":20,"Title":"Swimming","StaffId":20,"ContarctId":20,"DisciplineId":82},
  {"Id":21,"Title":"Winnie the Pooh","StaffId":21,"ContarctId":21,"DisciplineId":6},
  {"Id":22,"Title":"Screaming Skull, The","StaffId":22,"ContarctId":22,"DisciplineId":50},
  {"Id":23,"Title":"Little Brother, Big Trouble: A Christmas Adventure (Niko 2: Lentäjäveljekset)","StaffId":23,"ContarctId":23,"DisciplineId":49},
  {"Id":24,"Title":"City in the Sea","StaffId":24,"ContarctId":24,"DisciplineId":43},
  {"Id":25,"Title":"Dorm Daze (National Lampoon Presents Dorm Daze)","StaffId":25,"ContarctId":25,"DisciplineId":9},
  {"Id":26,"Title":"Net 2.0, The ","StaffId":26,"ContarctId":26,"DisciplineId":11},
  {"Id":27,"Title":"Othello (Tragedy of Othello: The Moor of Venice, The)","StaffId":27,"ContarctId":27,"DisciplineId":10},
  {"Id":28,"Title":"For Love and Gold (L'armata Brancaleone)","StaffId":28,"ContarctId":28,"DisciplineId":9},
  {"Id":29,"Title":"Real McCoy, The","StaffId":29,"ContarctId":29,"DisciplineId":21},
  {"Id":30,"Title":"North Face (Nordwand)","StaffId":30,"ContarctId":30,"DisciplineId":47}],
  "activities":[{"Id":1,"Code":"IDR","Name":"Erick","Description":"12/21/2017","MilestoneId":"1"},
  {"Id":2,"Code":"YER","Name":"Charissa","Description":"3/7/2018","MilestoneId":"2"},
  {"Id":3,"Code":"EUR","Name":"Enrichetta","Description":"3/11/2018","MilestoneId":"3"},
  {"Id":4,"Code":"EUR","Name":"Erinna","Description":"12/25/2017","MilestoneId":"4"},
  {"Id":5,"Code":"CZK","Name":"Lucienne","Description":"8/19/2018","MilestoneId":"5"},
  {"Id":6,"Code":"UZS","Name":"Carline","Description":"9/9/2018","MilestoneId":"6"},
  {"Id":7,"Code":"CNY","Name":"Grazia","Description":"9/14/2018","MilestoneId":"7"},
  {"Id":8,"Code":"CAD","Name":"Noble","Description":"6/30/2018","MilestoneId":"8"},
  {"Id":9,"Code":"IDR","Name":"Norrie","Description":"11/2/2018","MilestoneId":"9"},
  {"Id":10,"Code":"CNY","Name":"Christi","Description":"5/30/2018","MilestoneId":"10"},
  {"Id":11,"Code":"IDR","Name":"Leonerd","Description":"8/11/2018","MilestoneId":"11"},
  {"Id":12,"Code":"EUR","Name":"Xavier","Description":"10/24/2018","MilestoneId":"12"},
  {"Id":13,"Code":"UAH","Name":"Abie","Description":"4/6/2018","MilestoneId":"13"},
  {"Id":14,"Code":"PLN","Name":"Jdavie","Description":"10/19/2018","MilestoneId":"14"},
  {"Id":15,"Code":"RUB","Name":"Elvira","Description":"10/21/2018","MilestoneId":"15"},
  {"Id":16,"Code":"EUR","Name":"Roderick","Description":"2/26/2018","MilestoneId":"16"},
  {"Id":17,"Code":"RUB","Name":"Bill","Description":"1/18/2018","MilestoneId":"17"},
  {"Id":18,"Code":"CNY","Name":"Jacquette","Description":"10/14/2018","MilestoneId":"18"},
  {"Id":19,"Code":"PHP","Name":"Odelle","Description":"3/18/2018","MilestoneId":"19"},
  {"Id":20,"Code":"IDR","Name":"Mel","Description":"6/3/2018","MilestoneId":"20"},
  {"Id":21,"Code":"EUR","Name":"Madalyn","Description":"1/24/2018","MilestoneId":"21"},
  {"Id":22,"Code":"MXN","Name":"Richmound","Description":"5/4/2018","MilestoneId":"22"},
  {"Id":23,"Code":"CNY","Name":"Mable","Description":"7/12/2018","MilestoneId":"23"},
  {"Id":24,"Code":"PHP","Name":"Avivah","Description":"3/20/2018","MilestoneId":"24"},
  {"Id":25,"Code":"PEN","Name":"Priscella","Description":"7/1/2018","MilestoneId":"25"},
  {"Id":26,"Code":"IDR","Name":"Edna","Description":"8/22/2018","MilestoneId":"26"},
  {"Id":27,"Code":"CZK","Name":"Marabel","Description":"5/4/2018","MilestoneId":"27"},
  {"Id":28,"Code":"IDR","Name":"Margeaux","Description":"6/22/2018","MilestoneId":"28"},
  {"Id":29,"Code":"SEK","Name":"Sky","Description":"1/12/2018","MilestoneId":"29"},
  {"Id":30,"Code":"CNY","Name":"Quinn","Description":"8/14/2018","MilestoneId":"30"}]
  
}
